igneous/__init__.py
igneous/downsample_scales.py
igneous/secrets.py
igneous/shards.py
igneous/task_execution.py
igneous/types.py
igneous/scripts/remap2npy.py
igneous/scripts/validate_provenance.py
igneous/task_creation/__init__.py
igneous/task_creation/common.py
igneous/task_creation/image.py
igneous/task_creation/mesh.py
igneous/task_creation/obsolete.py
igneous/task_creation/setup.py
igneous/task_creation/skeleton.py
igneous/tasks/__init__.py
igneous/tasks/skeleton.py
igneous/tasks/spatial_index.py
igneous/tasks/watershed.py
igneous/tasks/image/__init__.py
igneous/tasks/image/ccl.py
igneous/tasks/image/image.py
igneous/tasks/image/obsolete.py
igneous/tasks/mesh/__init__.py
igneous/tasks/mesh/draco.py
igneous/tasks/mesh/mesh.py
igneous/tasks/mesh/mesh_graphene_remap.py
igneous/tasks/mesh/multires.py
igneous_cli/LICENSE
igneous_cli/__init__.py
igneous_cli/cli.py
igneous_cli/humanbytes.py
igneous_pipeline-4.34.0.dist-info/licenses/AUTHORS
igneous_pipeline-4.34.0.dist-info/licenses/LICENSE
igneous_pipeline-4.34.0.dist-info/METADATA
igneous_pipeline-4.34.0.dist-info/WHEEL
igneous_pipeline-4.34.0.dist-info/entry_points.txt
igneous_pipeline-4.34.0.dist-info/pbr.json
igneous_pipeline-4.34.0.dist-info/top_level.txt
igneous_pipeline-4.34.0.dist-info/RECORD
