Metadata-Version: 2.4
Name: igneous_pipeline
Version: 4.34.0
Summary: Manage, Downsample, Mesh, Skeletonize, and Transform Neuroglancer Datasets
Home-page: https://github.com/seung-lab/igneous/
Author: Ignacio Tartavull, William Silversmith, and others
Author-email: ws9@princeton.edu
License: GPL-3.0-or-later
Classifier: Intended Audience :: Developers
Classifier: Development Status :: 5 - Production/Stable
Classifier: Programming Language :: Python
Classifier: Programming Language :: Python :: 3
Classifier: Programming Language :: Python :: 3.9
Classifier: Programming Language :: Python :: 3.10
Classifier: Programming Language :: Python :: 3.11
Classifier: Programming Language :: Python :: 3.12
Classifier: Programming Language :: Python :: 3.13
Classifier: Topic :: Utilities
Classifier: Topic :: Scientific/Engineering :: Image Processing
License-File: LICENSE
License-File: AUTHORS
Requires-Dist: click>=6.7
Requires-Dist: cloud-files>=4.11.0
Requires-Dist: cloud-volume[all_codecs]>=12.5.0
Requires-Dist: crackle-codec
Requires-Dist: connected-components-3d>=3.10.1
Requires-Dist: dbscan
Requires-Dist: DracoPy<2.0.0,>=1.0.1
Requires-Dist: fastremap>=1.17.4
Requires-Dist: fastmorph>=1.4.1
Requires-Dist: google-cloud-logging
Requires-Dist: kimimaro[accel]>=5.4.0
Requires-Dist: mapbuffer>=0.7.1
Requires-Dist: networkx
Requires-Dist: numpy>=1.14.2
Requires-Dist: opencv-python-headless
Requires-Dist: pathos
Requires-Dist: Pillow>=4.2.1
Requires-Dist: pyfqmr
Requires-Dist: pytest>=3.3.1
Requires-Dist: pytz
Requires-Dist: scipy
Requires-Dist: shard-computer
Requires-Dist: tinybrain>=1.5.0
Requires-Dist: task-queue>=2.4.0
Requires-Dist: tqdm
Requires-Dist: trimesh[easy]
Requires-Dist: xs3d>=1.11.0
Requires-Dist: zmesh<2.0,>=1.4
Dynamic: author
Dynamic: author-email
Dynamic: classifier
Dynamic: description
Dynamic: description-content-type
Dynamic: home-page
Dynamic: license
Dynamic: license-file
Dynamic: requires-dist
Dynamic: summary
